Workbook

Sheet Leyenda
A1: Control de cuentas de trading
A3: Cómo usarla
A4: • Celdas AMARILLAS con texto azul: las rellenas tú.
A5: • Celdas blancas con texto negro: se calculan solas (no las toques).
A6: • La primera fila de datos de cada pestaña es un EJEMPLO: cámbiala o bórrala.
A8: Pestañas
A9: Cuentas: inventario y margen que te queda hasta el límite de pérdida de cada cuenta.
A10: Reglas: las reglas de cada prop firm. Verifícalas en su web: cambian a menudo.
A11: Diario: una fila por operación manual. Calcula el resultado en R (veces el riesgo).
A12: Semanal: revisión de cada viernes, una fila por cuenta. Cuenta tus operaciones del Diario.
A13: Gastos e ingresos: challenges, VPS, copiadores, suscripciones y pagos cobrados.
A15: Apex (drawdown trailing)
... A17: 'Nivel de liquidación' de la pestaña Cuentas cada vez que lo revises.

Sheet Cuentas
A1: Cuenta | B1: Firma / bróker | C1: Plataforma | D1: Tipo | E1: Uso | F1: Capital inicial ($) | G1: Balance actual ($) | H1: P/L ($) | I1: P/L % | J1: Nivel de liquidación ($) | K1: Margen hasta el límite ($) | L1: Margen % | M1: Riesgo máx. por operación (%) | N1: Riesgo máx. por operación ($) | O1: Estado | P1: Notas
A2: Pepperstone demo | B2: Pepperstone | C2: MT5 | D2: Demo | E2: IbsSwing (NAS100 + oro) | F2: 100000 | H2: =IF(OR(F2="",G2=""),"",G2-F2) | I2: =IF(OR(F2="",G2="",F2=0),"",H2/F2) | K2: =IF(OR(G2="",J2=""),"",G2-J2) | L2: =IF(OR(K2="",G2="",G2=0),"",K2/G2) | N2: =IF(OR(M2="",K2=""),"",MIN(M2*G2,K2)) | O2: Prueba | P2: EA con avisos de Telegram
A3: Alpaca paper | B3: Alpaca | C3: API | D3: Demo | E3: Largo plazo + cripto + IBS | F3: 100000 | G3: 100530.59 | H3: =IF(OR(F3="",G3=""),"",G3-F3) | I3: =IF(OR(F3="",G3="",F3=0),"",H3/F3) | K3: =IF(OR(G3="",J3=""),"",G3-J3) | L3: =IF(OR(K3="",G3="",G3=0),"",K3/G3) | N3: =IF(OR(M3="",K3=""),"",MIN(M3*G3,K3)) | O3: Prueba | P3: Balance del 2/10/2026
A4: Wall Street Funded | B4: Wall Street Funded | D4: Fondeada | E4: Manual | H4: =IF(OR(F4="",G4=""),"",G4-F4) | I4: =IF(OR(F4="",G4="",F4=0),"",H4/F4) | K4: =IF(OR(G4="",J4=""),"",G4-J4) | L4: =IF(OR(K4="",G4="",G4=0),"",K4/G4) | M4: 0.005 | N4: =IF(OR(M4="",K4=""),"",MIN(M4*G4,K4)) | O4: Activa
A5: Noctorial | B5: Noctorial | D5: Challenge | E5: Manual | H5: =IF(OR(F5="",G5=""),"",G5-F5) | I5: =IF(OR(F5="",G5="",F5=0),"",H5/F5) | K5: =IF(OR(G5="",J5=""),"",G5-J5) | L5: =IF(OR(K5="",G5="",G5=0),"",K5/G5) | M5: 0.01 | N5: =IF(OR(M5="",K5=""),"",MIN(M5*G5,K5)) | O5: En challenge
A6: Apex 1 | B6: Apex Trader Funding | C6: Tradovate | D6: Fondeada | E6: Manual | H6: =IF(OR(F6="",G6=""),"",G6-F6) | I6: =IF(OR(F6="",G6="",F6=0),"",H6/F6) | K6: =IF(OR(G6="",J6=""),"",G6-J6) | L6: =IF(OR(K6="",G6="",G6=0),"",K6/G6) | M6: 0.005 | N6: =IF(OR(M6="",K6=""),"",MIN(M6*G6,K6)) | O6: Activa | P6: Drawdown trailing: actualiza el nivel de liquidación
A7: Apex 2 | B7: Apex Trader Funding | C7: Tradovate | D7: Fondeada | E7: Manual | H7: =IF(OR(F7="",G7=""),"",G7-F7) | I7: =IF(OR(F7="",G7="",F7=0),"",H7/F7) | K7: =IF(OR(G7="",J7=""),"",G7-J7) | L7: =IF(OR(K7="",G7="",G7=0),"",K7/G7) | M7: 0.005 | N7: =IF(OR(M7="",K7=""),"",MIN(M7*G7,K7)) | O7: Activa | P7: Drawdown trailing: actualiza el nivel de liquidación
H8: =IF(OR(F8="",G8=""),"",G8-F8) | I8: =IF(OR(F8="",G8="",F8=0),"",H8/F8) | K8: =IF(OR(G8="",J8=""),"",G8-J8) | L8: =IF(OR(K8="",G8="",G8=0),"",K8/G8) | N8: =IF(OR(M8="",K8=""),"",MIN(M8*G8,K8))
H9: =IF(OR(F9="",G9=""),"",G9-F9) | I9: =IF(OR(F9="",G9="",F9=0),"",H9/F9) | K9: =IF(OR(G9="",J9=""),"",G9-J9) | L9: =IF(OR(K9="",G9="",G9=0),"",K9/G9) | N9: =IF(OR(M9="",K9=""),"",MIN(M9*G9,K9))
H10: =IF(OR(F10="",G10=""),"",G10-F10) | I10: =IF(OR(F10="",G10="",F10=0),"",H10/F10) | K10: =IF(OR(G10="",J10=""),"",G10-J10) | L10: =IF(OR(K10="",G10="",G10=0),"",K10/G10) | N10: =IF(OR(M10="",K10=""),"",MIN(M10*G10,K10))
H11: =IF(OR(F11="",G11=""),"",G11-F11) | I11: =IF(OR(F11="",G11="",F11=0),"",H11/F11) | K11: =IF(OR(G11="",J11=""),"",G11-J11) | L11: =IF(OR(K11="",G11="",G11=0),"",K11/G11) | N11: =IF(OR(M11="",K11=""),"",MIN(M11*G11,K11))
H12: =IF(OR(F12="",G12=""),"",G12-F12) | I12: =IF(OR(F12="",G12="",F12=0),"",H12/F12) | K12: =IF(OR(G12="",J12=""),"",G12-J12) | L12: =IF(OR(K12="",G12="",G12=0),"",K12/G12) | N12: =IF(OR(M12="",K12=""),"",MIN(M12*G12,K12))
H13: =IF(OR(F13="",G13=""),"",G13-F13) | I13: =IF(OR(F13="",G13="",F13=0),"",H13/F13) | K13: =IF(OR(G13="",J13=""),"",G13-J13) | L13: =IF(OR(K13="",G13="",G13=0),"",K13/G13) | N13: =IF(OR(M13="",K13=""),"",MIN(M13*G13,K13))
H14: =IF(OR(F14="",G14=""),"",G14-F14) | I14: =IF(OR(F14="",G14="",F14=0),"",H14/F14) | K14: =IF(OR(G14="",J14=""),"",G14-J14) | L14: =IF(OR(K14="",G14="",G14=0),"",K14/G14) | N14: =IF(OR(M14="",K14=""),"",MIN(M14*G14,K14))
H15: =IF(OR(F15="",G15=""),"",G15-F15) | I15: =IF(OR(F15="",G15="",F15=0),"",H15/F15) | K15: =IF(OR(G15="",J15=""),"",G15-J15) | L15: =IF(OR(K15="",G15="",G15=0),"",K15/G15) | N15: =IF(OR(M15="",K15=""),"",MIN(M15*G15,K15))
H16: =IF(OR(F16="",G16=""),"",G16-F16) | I16: =IF(OR(F16="",G16="",F16=0),"",H16/F16) | K16: =IF(OR(G16="",J16=""),"",G16-J16) | L16: =IF(OR(K16="",G16="",G16=0),"",K16/G16) | N16: =IF(OR(M16="",K16=""),"",MIN(M16*G16,K16))
H17: =IF(OR(F17="",G17=""),"",G17-F17) | I17: =IF(OR(F17="",G17="",F17=0),"",H17/F17) | K17: =IF(OR(G17="",J17=""),"",G17-J17) | L17: =IF(OR(K17="",G17="",G17=0),"",K17/G17) | N17: =IF(OR(M17="",K17=""),"",MIN(M17*G17,K17))
H18: =IF(OR(F18="",G18=""),"",G18-F18) | I18: =IF(OR(F18="",G18="",F18=0),"",H18/F18) | K18: =IF(OR(G18="",J18=""),"",G18-J18) | L18: =IF(OR(K18="",G18="",G18=0),"",K18/G18) | N18: =IF(OR(M18="",K18=""),"",MIN(M18*G18,K18))
H19: =IF(OR(F19="",G19=""),"",G19-F19) | I19: =IF(OR(F19="",G19="",F19=0),"",H19/F19) | K19: =IF(OR(G19="",J19=""),"",G19-J19) | L19: =IF(OR(K19="",G19="",G19=0),"",K19/G19) | N19: =IF(OR(M19="",K19=""),"",MIN(M19*G19,K19))
... H21: =IF(OR(F21="",G21=""),"",G21-F21) | I21: =IF(OR(F21="",G21="",F21=0),"",H21/F21) | K21: =IF(OR(G21="",J21=""),"",G21-J21) | L21: =IF(OR(K21="",G21="",G21=0),"",K21/G21) | N21: =IF(OR(M21="",K21=""),"",MIN(M21*G21,K21))

Sheet Reglas
A1: Firma | B1: Cuenta / programa | C1: Objetivo de beneficio (%) | D1: Pérdida diaria máx. (%) | E1: Pérdida total máx. (%) | F1: Tipo de drawdown | G1: ¿Overnight / fin de semana? | H1: ¿Copy trading entre cuentas propias? | I1: ¿EAs / bots? | J1: Días mínimos | K1: Regla de consistencia | L1: Hora límite de cierre | M1: Verificado el | N1: Fuente / notas
A2: Crypto Fund Trader | B2: 2 fases | C2: 0.08 | D2: 0.05 | E2: 0.12 | F2: Fijo (fase 1) | G2: Sí | H2: Sí | I2: Sí | N2: Ejemplo según reseñas de 2026 (LuxAlgo, Tradelytic). Fase 2: objetivo 4%. Verificar en su web.
A3: Wall Street Funded
A4: Noctorial | B4: Challenge
A5: Apex Trader Funding | B5: PA (fondeada) | N5: Completar desde la web de Apex: drawdown trailing, cierre diario obligatorio, consistencia y pagos.

Sheet Diario
A1: Fecha | B1: Cuenta | C1: Instrumento | D1: Dirección | E1: Contratos / lotes | F1: Entrada | G1: Stop | H1: Salida | I1: Resultado ($) | J1: Riesgo ($) | K1: Resultado (R) | L1: Setup | M1: ¿Seguí el plan? | N1: Notas
A2: 46300 | B2: Apex 1 | C2: MNQ | D2: Compra | E2: 2 | F2: 30120.25 | G2: 30095.25 | H2: 30170.25 | I2: 200 | J2: 100 | K2: =IF(OR(I2="",J2="",J2=0),"",I2/J2) | L2: Ruptura apertura | M2: Sí | N2: Ejemplo: bórrala cuando empieces
K3: =IF(OR(I3="",J3="",J3=0),"",I3/J3)
K4: =IF(OR(I4="",J4="",J4=0),"",I4/J4)
K5: =IF(OR(I5="",J5="",J5=0),"",I5/J5)
K6: =IF(OR(I6="",J6="",J6=0),"",I6/J6)
K7: =IF(OR(I7="",J7="",J7=0),"",I7/J7)
K8: =IF(OR(I8="",J8="",J8=0),"",I8/J8)
K9: =IF(OR(I9="",J9="",J9=0),"",I9/J9)
K10: =IF(OR(I10="",J10="",J10=0),"",I10/J10)
K11: =IF(OR(I11="",J11="",J11=0),"",I11/J11)
K12: =IF(OR(I12="",J12="",J12=0),"",I12/J12)
K13: =IF(OR(I13="",J13="",J13=0),"",I13/J13)
K14: =IF(OR(I14="",J14="",J14=0),"",I14/J14)
... K301: =IF(OR(I301="",J301="",J301=0),"",I301/J301)

Sheet Semanal
A1: Semana (lunes) | B1: Cuenta | C1: Balance inicio ($) | D1: Balance fin ($) | E1: P/L ($) | F1: P/L % | G1: Operaciones | H1: Ganadoras | I1: % ganadoras | J1: Suma en R | K1: Margen hasta el límite ($) | L1: Notas
A2: 46300 | B2: Apex 1 | C2: 50000 | D2: 50200 | E2: =IF(OR(C2="",D2=""),"",D2-C2) | F2: =IF(OR(C2="",D2="",C2=0),"",E2/C2) | G2: =IF(OR(A2="",B2=""),"",COUNTIFS(Diario!$B$2:$B$301,$B2,Diario!$A$2:$A$301,">="&$A2,Diario!$A$2:$A$301,"<"&$A2+7)) | H2: =IF(OR(A2="",B2=""),"",COUNTIFS(Diario!$B$2:$B$301,$B2,Diario!$A$2:$A$301,">="&$A2,Diario!$A$2:$A$301,"<"&$A2+7,Diario!$I$2:$I$301,">0")) | I2: =IF(OR(G2="",G2=0),"",H2/G2) | J2: =IF(OR(A2="",B2=""),"",SUMIFS(Diario!$K$2:$K$301,Diario!$B$2:$B$301,$B2,Diario!$A$2:$A$301,">="&$A2,Diario!$A$2:$A$301,"<"&$A2+7)) | K2: =IF(OR(D2="",B2=""),"",IFERROR(IF(INDEX(Cuentas!$J$2:$J$21,MATCH(B2,Cuentas!$A$2:$A$21,0))="","",D2-INDEX(Cuentas!$J$2:$J$21,MATCH(B2,Cuentas!$A$2:$A$21,0))),"")) | L2: Ejemplo: bórrala cuando empieces
E3: =IF(OR(C3="",D3=""),"",D3-C3) | F3: =IF(OR(C3="",D3="",C3=0),"",E3/C3) | G3: =IF(OR(A3="",B3=""),"",COUNTIFS(Diario!$B$2:$B$301,$B3,Diario!$A$2:$A$301,">="&$A3,Diario!$A$2:$A$301,"<"&$A3+7)) | H3: =IF(OR(A3="",B3=""),"",COUNTIFS(Diario!$B$2:$B$301,$B3,Diario!$A$2:$A$301,">="&$A3,Diario!$A$2:$A$301,"<"&$A3+7,Diario!$I$2:$I$301,">0")) | I3: =IF(OR(G3="",G3=0),"",H3/G3) | J3: =IF(OR(A3="",B3=""),"",SUMIFS(Diario!$K$2:$K$301,Diario!$B$2:$B$301,$B3,Diario!$A$2:$A$301,">="&$A3,Diario!$A$2:$A$301,"<"&$A3+7)) | K3: =IF(OR(D3="",B3=""),"",IFERROR(IF(INDEX(Cuentas!$J$2:$J$21,MATCH(B3,Cuentas!$A$2:$A$21,0))="","",D3-INDEX(Cuentas!$J$2:$J$21,MATCH(B3,Cuentas!$A$2:$A$21,0))),""))
E4: =IF(OR(C4="",D4=""),"",D4-C4) | F4: =IF(OR(C4="",D4="",C4=0),"",E4/C4) | G4: =IF(OR(A4="",B4=""),"",COUNTIFS(Diario!$B$2:$B$301,$B4,Diario!$A$2:$A$301,">="&$A4,Diario!$A$2:$A$301,"<"&$A4+7)) | H4: =IF(OR(A4="",B4=""),"",COUNTIFS(Diario!$B$2:$B$301,$B4,Diario!$A$2:$A$301,">="&$A4,Diario!$A$2:$A$301,"<"&$A4+7,Diario!$I$2:$I$301,">0")) | I4: =IF(OR(G4="",G4=0),"",H4/G4) | J4: =IF(OR(A4="",B4=""),"",SUMIFS(Diario!$K$2:$K$301,Diario!$B$2:$B$301,$B4,Diario!$A$2:$A$301,">="&$A4,Diario!$A$2:$A$301,"<"&$A4+7)) | K4: =IF(OR(D4="",B4=""),"",IFERROR(IF(INDEX(Cuentas!$J$2:$J$21,MATCH(B4,Cuentas!$A$2:$A$21,0))="","",D4-INDEX(Cuentas!$J$2:$J$21,MATCH(B4,Cuentas!$A$2:$A$21,0))),""))
E5: =IF(OR(C5="",D5=""),"",D5-C5) | F5: =IF(OR(C5="",D5="",C5=0),"",E5/C5) | G5: =IF(OR(A5="",B5=""),"",COUNTIFS(Diario!$B$2:$B$301,$B5,Diario!$A$2:$A$301,">="&$A5,Diario!$A$2:$A$301,"<"&$A5+7)) | H5: =IF(OR(A5="",B5=""),"",COUNTIFS(Diario!$B$2:$B$301,$B5,Diario!$A$2:$A$301,">="&$A5,Diario!$A$2:$A$301,"<"&$A5+7,Diario!$I$2:$I$301,">0")) | I5: =IF(OR(G5="",G5=0),"",H5/G5) | J5: =IF(OR(A5="",B5=""),"",SUMIFS(Diario!$K$2:$K$301,Diario!$B$2:$B$301,$B5,Diario!$A$2:$A$301,">="&$A5,Diario!$A$2:$A$301,"<"&$A5+7)) | K5: =IF(OR(D5="",B5=""),"",IFERROR(IF(INDEX(Cuentas!$J$2:$J$21,MATCH(B5,Cuentas!$A$2:$A$21,0))="","",D5-INDEX(Cuentas!$J$2:$J$21,MATCH(B5,Cuentas!$A$2:$A$21,0))),""))
E6: =IF(OR(C6="",D6=""),"",D6-C6) | F6: =IF(OR(C6="",D6="",C6=0),"",E6/C6) | G6: =IF(OR(A6="",B6=""),"",COUNTIFS(Diario!$B$2:$B$301,$B6,Diario!$A$2:$A$301,">="&$A6,Diario!$A$2:$A$301,"<"&$A6+7)) | H6: =IF(OR(A6="",B6=""),"",COUNTIFS(Diario!$B$2:$B$301,$B6,Diario!$A$2:$A$301,">="&$A6,Diario!$A$2:$A$301,"<"&$A6+7,Diario!$I$2:$I$301,">0")) | I6: =IF(OR(G6="",G6=0),"",H6/G6) | J6: =IF(OR(A6="",B6=""),"",SUMIFS(Diario!$K$2:$K$301,Diario!$B$2:$B$301,$B6,Diario!$A$2:$A$301,">="&$A6,Diario!$A$2:$A$301,"<"&$A6+7)) | K6: =IF(OR(D6="",B6=""),"",IFERROR(IF(INDEX(Cuentas!$J$2:$J$21,MATCH(B6,Cuentas!$A$2:$A$21,0))="","",D6-INDEX(Cuentas!$J$2:$J$21,MATCH(B6,Cuentas!$A$2:$A$21,0))),""))
E7: =IF(OR(C7="",D7=""),"",D7-C7) | F7: =IF(OR(C7="",D7="",C7=0),"",E7/C7) | G7: =IF(OR(A7="",B7=""),"",COUNTIFS(Diario!$B$2:$B$301,$B7,Diario!$A$2:$A$301,">="&$A7,Diario!$A$2:$A$301,"<"&$A7+7)) | H7: =IF(OR(A7="",B7=""),"",COUNTIFS(Diario!$B$2:$B$301,$B7,Diario!$A$2:$A$301,">="&$A7,Diario!$A$2:$A$301,"<"&$A7+7,Diario!$I$2:$I$301,">0")) | I7: =IF(OR(G7="",G7=0),"",H7/G7) | J7: =IF(OR(A7="",B7=""),"",SUMIFS(Diario!$K$2:$K$301,Diario!$B$2:$B$301,$B7,Diario!$A$2:$A$301,">="&$A7,Diario!$A$2:$A$301,"<"&$A7+7)) | K7: =IF(OR(D7="",B7=""),"",IFERROR(IF(INDEX(Cuentas!$J$2:$J$21,MATCH(B7,Cuentas!$A$2:$A$21,0))="","",D7-INDEX(Cuentas!$J$2:$J$21,MATCH(B7,Cuentas!$A$2:$A$21,0))),""))
E8: =IF(OR(C8="",D8=""),"",D8-C8) | F8: =IF(OR(C8="",D8="",C8=0),"",E8/C8) | G8: =IF(OR(A8="",B8=""),"",COUNTIFS(Diario!$B$2:$B$301,$B8,Diario!$A$2:$A$301,">="&$A8,Diario!$A$2:$A$301,"<"&$A8+7)) | H8: =IF(OR(A8="",B8=""),"",COUNTIFS(Diario!$B$2:$B$301,$B8,Diario!$A$2:$A$301,">="&$A8,Diario!$A$2:$A$301,"<"&$A8+7,Diario!$I$2:$I$301,">0")) | I8: =IF(OR(G8="",G8=0),"",H8/G8) | J8: =IF(OR(A8="",B8=""),"",SUMIFS(Diario!$K$2:$K$301,Diario!$B$2:$B$301,$B8,Diario!$A$2:$A$301,">="&$A8,Diario!$A$2:$A$301,"<"&$A8+7)) | K8: =IF(OR(D8="",B8=""),"",IFERROR(IF(INDEX(Cuentas!$J$2:$J$21,MATCH(B8,Cuentas!$A$2:$A$21,0))="","",D8-INDEX(Cuentas!$J$2:$J$21,MATCH(B8,Cuentas!$A$2:$A$21,0))),""))
E9: =IF(OR(C9="",D9=""),"",D9-C9) | F9: =IF(OR(C9="",D9="",C9=0),"",E9/C9) | G9: =IF(OR(A9="",B9=""),"",COUNTIFS(Diario!$B$2:$B$301,$B9,Diario!$A$2:$A$301,">="&$A9,Diario!$A$2:$A$301,"<"&$A9+7)) | H9: =IF(OR(A9="",B9=""),"",COUNTIFS(Diario!$B$2:$B$301,$B9,Diario!$A$2:$A$301,">="&$A9,Diario!$A$2:$A$301,"<"&$A9+7,Diario!$I$2:$I$301,">0")) | I9: =IF(OR(G9="",G9=0),"",H9/G9) | J9: =IF(OR(A9="",B9=""),"",SUMIFS(Diario!$K$2:$K$301,Diario!$B$2:$B$301,$B9,Diario!$A$2:$A$301,">="&$A9,Diario!$A$2:$A$301,"<"&$A9+7)) | K9: =IF(OR(D9="",B9=""),"",IFERROR(IF(INDEX(Cuentas!$J$2:$J$21,MATCH(B9,Cuentas!$A$2:$A$21,0))="","",D9-INDEX(Cuentas!$J$2:$J$21,MATCH(B9,Cuentas!$A$2:$A$21,0))),""))
E10: =IF(OR(C10="",D10=""),"",D10-C10) | F10: =IF(OR(C10="",D10="",C10=0),"",E10/C10) | G10: =IF(OR(A10="",B10=""),"",COUNTIFS(Diario!$B$2:$B$301,$B10,Diario!$A$2:$A$301,">="&$A10,Diario!$A$2:$A$301,"<"&$A10+7)) | H10: =IF(OR(A10="",B10=""),"",COUNTIFS(Diario!$B$2:$B$301,$B10,Diario!$A$2:$A$301,">="&$A10,Diario!$A$2:$A$301,"<"&$A10+7,Diario!$I$2:$I$301,">0")) | I10: =IF(OR(G10="",G10=0),"",H10/G10) | J10: =IF(OR(A10="",B10=""),"",SUMIFS(Diario!$K$2:$K$301,Diario!$B$2:$B$301,$B10,Diario!$A$2:$A$301,">="&$A10,Diario!$A$2:$A$301,"<"&$A10+7)) | K10: =IF(OR(D10="",B10=""),"",IFERROR(IF(INDEX(Cuentas!$J$2:$J$21,MATCH(B10,Cuentas!$A$2:$A$21,0))="","",D10-INDEX(Cuentas!$J$2:$J$21,MATCH(B10,Cuentas!$A$2:$A$21,0))),""))
E11: =IF(OR(C11="",D11=""),"",D11-C11) | F11: =IF(OR(C11="",D11="",C11=0),"",E11/C11) | G11: =IF(OR(A11="",B11=""),"",COUNTIFS(Diario!$B$2:$B$301,$B11,Diario!$A$2:$A$301,">="&$A11,Diario!$A$2:$A$301,"<"&$A11+7)) | H11: =IF(OR(A11="",B11=""),"",COUNTIFS(Diario!$B$2:$B$301,$B11,Diario!$A$2:$A$301,">="&$A11,Diario!$A$2:$A$301,"<"&$A11+7,Diario!$I$2:$I$301,">0")) | I11: =IF(OR(G11="",G11=0),"",H11/G11) | J11: =IF(OR(A11="",B11=""),"",SUMIFS(Diario!$K$2:$K$301,Diario!$B$2:$B$301,$B11,Diario!$A$2:$A$301,">="&$A11,Diario!$A$2:$A$301,"<"&$A11+7)) | K11: =IF(OR(D11="",B11=""),"",IFERROR(IF(INDEX(Cuentas!$J$2:$J$21,MATCH(B11,Cuentas!$A$2:$A$21,0))="","",D11-INDEX(Cuentas!$J$2:$J$21,MATCH(B11,Cuentas!$A$2:$A$21,0))),""))
E12: =IF(OR(C12="",D12=""),"",D12-C12) | F12: =IF(OR(C12="",D12="",C12=0),"",E12/C12) | G12: =IF(OR(A12="",B12=""),"",COUNTIFS(Diario!$B$2:$B$301,$B12,Diario!$A$2:$A$301,">="&$A12,Diario!$A$2:$A$301,"<"&$A12+7)) | H12: =IF(OR(A12="",B12=""),"",COUNTIFS(Diario!$B$2:$B$301,$B12,Diario!$A$2:$A$301,">="&$A12,Diario!$A$2:$A$301,"<"&$A12+7,Diario!$I$2:$I$301,">0")) | I12: =IF(OR(G12="",G12=0),"",H12/G12) | J12: =IF(OR(A12="",B12=""),"",SUMIFS(Diario!$K$2:$K$301,Diario!$B$2:$B$301,$B12,Diario!$A$2:$A$301,">="&$A12,Diario!$A$2:$A$301,"<"&$A12+7)) | K12: =IF(OR(D12="",B12=""),"",IFERROR(IF(INDEX(Cuentas!$J$2:$J$21,MATCH(B12,Cuentas!$A$2:$A$21,0))="","",D12-INDEX(Cuentas!$J$2:$J$21,MATCH(B12,Cuentas!$A$2:$A$21,0))),""))
E13: =IF(OR(C13="",D13=""),"",D13-C13) | F13: =IF(OR(C13="",D13="",C13=0),"",E13/C13) | G13: =IF(OR(A13="",B13=""),"",COUNTIFS(Diario!$B$2:$B$301,$B13,Diario!$A$2:$A$301,">="&$A13,Diario!$A$2:$A$301,"<"&$A13+7)) | H13: =IF(OR(A13="",B13=""),"",COUNTIFS(Diario!$B$2:$B$301,$B13,Diario!$A$2:$A$301,">="&$A13,Diario!$A$2:$A$301,"<"&$A13+7,Diario!$I$2:$I$301,">0")) | I13: =IF(OR(G13="",G13=0),"",H13/G13) | J13: =IF(OR(A13="",B13=""),"",SUMIFS(Diario!$K$2:$K$301,Diario!$B$2:$B$301,$B13,Diario!$A$2:$A$301,">="&$A13,Diario!$A$2:$A$301,"<"&$A13+7)) | K13: =IF(OR(D13="",B13=""),"",IFERROR(IF(INDEX(Cuentas!$J$2:$J$21,MATCH(B13,Cuentas!$A$2:$A$21,0))="","",D13-INDEX(Cuentas!$J$2:$J$21,MATCH(B13,Cuentas!$A$2:$A$21,0))),""))
E14: =IF(OR(C14="",D14=""),"",D14-C14) | F14: =IF(OR(C14="",D14="",C14=0),"",E14/C14) | G14: =IF(OR(A14="",B14=""),"",COUNTIFS(Diario!$B$2:$B$301,$B14,Diario!$A$2:$A$301,">="&$A14,Diario!$A$2:$A$301,"<"&$A14+7)) | H14: =IF(OR(A14="",B14=""),"",COUNTIFS(Diario!$B$2:$B$301,$B14,Diario!$A$2:$A$301,">="&$A14,Diario!$A$2:$A$301,"<"&$A14+7,Diario!$I$2:$I$301,">0")) | I14: =IF(OR(G14="",G14=0),"",H14/G14) | J14: =IF(OR(A14="",B14=""),"",SUMIFS(Diario!$K$2:$K$301,Diario!$B$2:$B$301,$B14,Diario!$A$2:$A$301,">="&$A14,Diario!$A$2:$A$301,"<"&$A14+7)) | K14: =IF(OR(D14="",B14=""),"",IFERROR(IF(INDEX(Cuentas!$J$2:$J$21,MATCH(B14,Cuentas!$A$2:$A$21,0))="","",D14-INDEX(Cuentas!$J$2:$J$21,MATCH(B14,Cuentas!$A$2:$A$21,0))),""))
... E151: =IF(OR(C151="",D151=""),"",D151-C151) | F151: =IF(OR(C151="",D151="",C151=0),"",E151/C151) | G151: =IF(OR(A151="",B151=""),"",COUNTIFS(Diario!$B$2:$B$301,$B151,Diario!$A$2:$A$301,">="&$A151,Diario!$A$2:$A$301,"<"&$A151+7)) | H151: =IF(OR(A151="",B151=""),"",COUNTIFS(Diario!$B$2:$B$301,$B151,Diario!$A$2:$A$301,">="&$A151,Diario!$A$2:$A$301,"<"&$A151+7,Diario!$I$2:$I$301,">0")) | I151: =IF(OR(G151="",G151=0),"",H151/G151) | J151: =IF(OR(A151="",B151=""),"",SUMIFS(Diario!$K$2:$K$301,Diario!$B$2:$B$301,$B151,Diario!$A$2:$A$301,">="&$A151,Diario!$A$2:$A$301,"<"&$A151+7)) | K151: =IF(OR(D151="",B151=""),"",IFERROR(IF(INDEX(Cuentas!$J$2:$J$21,MATCH(B151,Cuentas!$A$2:$A$21,0))="","",D151-INDEX(Cuentas!$J$2:$J$21,MATCH(B151,Cuentas!$A$2:$A$21,0))),""))

Sheet Gastos e ingresos
A1: Fecha | B1: Concepto | C1: Firma / proveedor | D1: Tipo | E1: Importe ($) | F1: Notas
A2: 46296 | B2: Challenge 2 fases 100k | C2: Noctorial | D2: Gasto | E2: 0 | F2: Ejemplo: pon el importe real | H2: Resumen
H3: Total gastos | I3: =SUMIF($D$2:$D$201,"Gasto",$E$2:$E$201)
H4: Total ingresos | I4: =SUMIF($D$2:$D$201,"Ingreso",$E$2:$E$201)
H5: Neto | I5: =I4-I3
